usuarios_cpf_django-0.0.2.dist-info/METADATA
usuarios_cpf_django-0.0.2.dist-info/RECORD
usuarios_cpf_django-0.0.2.dist-info/WHEEL
usuarios_cpf_django-0.0.2.dist-info/top_level.txt
usuarios_semus/__init__.py
usuarios_semus/admin.py
usuarios_semus/apps.py
usuarios_semus/managers.py
usuarios_semus/models.py
usuarios_semus/tests.py
usuarios_semus/validators.py
usuarios_semus/views.py
usuarios_semus/migrations/0001_initial.py
usuarios_semus/migrations/__init__.py
