Metadata-Version: 2.1
Name: usuarios-cpf-django
Version: 0.0.2
Summary: Gerenciamento de usuarios para apps Djando na semus
Home-page: https://gitlab.com/semus/django-utils/usuarios_semus
Author: Paulo Roberto Cruz
Author-email: paulo.cruz9@gmail.com
License: BSD
Download-URL: https://gitlab.com/semus/django-utils/usuarios_semus
Platform: UNKNOWN
Classifier: Development Status :: 5 - Production/Stable
Classifier: Environment :: Web Environment
Classifier: Framework :: Django
Classifier: Intended Audience :: Developers
Classifier: License :: OSI Approved :: BSD License
Classifier: Operating System :: OS Independent
Classifier: Programming Language :: Python
Classifier: Topic :: Security
Classifier: Programming Language :: Python :: 3.5
Classifier: Programming Language :: Python :: 3.6
Classifier: Programming Language :: Python :: 3.7
Classifier: Programming Language :: Python :: 3.8
Classifier: Programming Language :: Python :: 3 :: Only
Requires-Python: >=3.5
Requires-Dist: Django (>=3.0)
Requires-Dist: pycpfcnpj (==1.5.1)
